maptrans/mt.py
maptrans/lib/fio.py
maptrans-0.3.0.dist-info/METADATA
maptrans-0.3.0.dist-info/WHEEL
maptrans-0.3.0.dist-info/entry_points.txt
maptrans-0.3.0.dist-info/RECORD
