Metadata-Version: 2.4
Name: maptrans
Version: 0.3.0
Summary: Map Transform tool
Requires-Python: >=3.10
Requires-Dist: requests>=2.32.4
